okolab/__init__.py
okolab/__main__.py
okolab/device.py
okolab/util.py
okolab-0.2.1.dist-info/METADATA
okolab-0.2.1.dist-info/WHEEL
okolab-0.2.1.dist-info/top_level.txt
okolab-0.2.1.dist-info/RECORD
