Metadata-Version: 2.1
Name: okolab
Version: 0.2.1
Summary: A Python package that provides control of the H401-T-CONTROLLER temperature controller from Okolab
License: EUPL-1.2
Project-URL: repository, https://github.com/slietar/okolab
Requires-Python: >=3.11
Requires-Dist: pyserial (<4,>=3.5)
